Metadata-Version: 1.2
Name: discord.gui
Version: 1.0.2
Summary: A discord.py extension providing a GUI interface to monitor the bot and modify command settings
Home-page: https://github.com/Starwort/discord.gui
Author: Starwort
License: GNU GPL 3
Project-URL: Code, https://github.com/Starwort/discord.gui
Project-URL: Issue tracker, https://github.com/Starwort/discord.gui/issues
Keywords: discord.gui discord.py discord cog gui extension
Platform: UNKNOWN
Classifier: Development Status :: 4 - Beta
Classifier: Framework :: AsyncIO
Classifier: Intended Audience :: Developers
Classifier: Natural Language :: English
Classifier: Operating System :: OS Independent
Classifier: Programming Language :: Python :: 3 :: Only
Classifier: Programming Language :: Python :: 3.6
Classifier: Programming Language :: Python :: 3.7
Classifier: Programming Language :: Python :: 3.8
Classifier: Topic :: Communications :: Chat
Classifier: Topic :: Internet
Classifier: Topic :: Software Development :: Debuggers
Classifier: Topic :: Software Development :: Testing
Classifier: Topic :: Utilities
Requires-Python: >=3.6.0
